[
  {
    "name": "Synth 1",
    "type": "Synth",
    "settings": {
      "volume": "0",
      "detune": "0",
      "portamento": "0.4",
      "envelope": {
        "attack": "2",
        "attackCurve": "linear",
        "decay": "0.1",
        "decayCurve": "exponential",
        "release": "1",
        "releaseCurve": "exponential",
        "sustain": "0.3"
      },
      "oscillator": {
        "partialCount": "0",
        "partials": [],
        "phase": 0,
        "type": "square"
      }
    }
  },
  {
    "name": "Synth 2",
    "type": "Synth",
    "settings": {
      "volume": "0",
      "detune": "0",
      "portamento": "0",
      "envelope": {
        "attack": "1",
        "attackCurve": "linear",
        "decay": "0.1",
        "decayCurve": "exponential",
        "release": "1",
        "releaseCurve": "exponential",
        "sustain": "0.3"
      },
      "oscillator": {
        "partialCount": "0",
        "partials": [],
        "phase": 0,
        "type": "triangle"
      }
    }
  },
  {
    "name": "Default 2",
    "type": "Synth",
    "settings": {
      "volume": "0",
      "detune": "0",
      "portamento": "1",
      "envelope": {
        "attack": "2",
        "attackCurve": "linear",
        "decay": "0.1",
        "decayCurve": "exponential",
        "release": "1",
        "releaseCurve": "exponential",
        "sustain": "0.3"
      },
      "oscillator": {
        "partialCount": "0",
        "partials": [],
        "phase": 0,
        "type": "triangle"
      }
    }
  }
]
